{"id":"planka","name":"Planka","description":{"ko":"칸반 보드 프로젝트 관리 (Trello 대안)","en":"Kanban board project management (Trello alternative)"},"category":"productivity","version":"1.0.0","website":"https://planka.app","source":"https://github.com/plankanban/planka","icon":"https://raw.githubusercontent.com/plankanban/planka/master/client/public/logo192.png","ports":[1337],"features":[{"title":{"ko":"칸반 보드","en":"Kanban board"},"description":{"ko":"드래그 앤 드롭 태스크 관리","en":"Drag and drop task management"},"icon":"📋"},{"title":{"ko":"실시간 협업","en":"Real-time collaboration"},"description":{"ko":"팀원과 실시간 보드 공유","en":"Share boards with team in real-time"},"icon":"👥"},{"title":{"ko":"첨부 파일","en":"Attachments"},"description":{"ko":"카드에 파일 첨부","en":"Attach files to cards"},"icon":"📎"},{"title":{"ko":"라벨/체크리스트","en":"Labels/Checklists"},"description":{"ko":"라벨, 기한, 체크리스트로 태스크 관리","en":"Manage tasks with labels, due dates, checklists"},"icon":"✅"}],"env":[{"key":"PORT","label":{"ko":"외부 포트","en":"External Port"},"type":"port","default":"1337"},{"key":"SECRET_KEY","label":{"ko":"시크릿 키","en":"Secret Key"},"type":"password","required":true,"generate":true},{"key":"ADMIN_EMAIL","label":{"ko":"관리자 이메일","en":"Admin Email"},"type":"text","default":"admin@example.com"},{"key":"ADMIN_PASSWORD","label":{"ko":"관리자 비밀번호","en":"Admin Password"},"type":"password","required":true,"generate":true}]}
